pyffm/__init__.py
pyffm/pyffm.py
pyffm/util.py
pyffm/engine/__init__.py
pyffm/engine/base_engine.py
pyffm/engine/ffm_engine.py
pyffm/engine/fm_engine.py
pyffm/engine/model/__init__.py
pyffm/engine/model/base_model.py
pyffm/engine/model/ffm_model.py
pyffm/engine/model/fm_model.py
pyffm/test/__init__.py
pyffm/test/test_ctrengine.py
pyffm/test/test_pyffm.py
pyffm/test/test_utils.py
pyffm/test/data/__init__.py
pyffm/test/integration_tests/__init__.py
pyffm/test/integration_tests/test_ctrengine.py
pyffm/test/integration_tests/test_pyffm.py
pyffm/test/unit_tests/__init__.py
pyffm/test/unit_tests/test_utils.py
pyFFM-0.0.7.dist-info/LICENSE
pyFFM-0.0.7.dist-info/METADATA
pyFFM-0.0.7.dist-info/WHEEL
pyFFM-0.0.7.dist-info/top_level.txt
pyFFM-0.0.7.dist-info/RECORD
