Metadata-Version: 2.1
Name: pyFFM
Version: 0.0.7
Summary: Python implementation of Factorization Machines (+ Field Aware)
Home-page: https://github.com/mascaroa/pyffm
Author: Aaron Mascaro
Author-email: mascaroa1@gmail.com
License: MIT
Platform: UNKNOWN
Requires-Dist: numpy (~=1.18)
Requires-Dist: pandas (~=1.4)
Requires-Dist: numba (~=0.55)
